bigfastapi/__init__.py
bigfastapi/activity_log.py
bigfastapi/api_key.py
bigfastapi/auth.py
bigfastapi/auth_api.py
bigfastapi/banks.py
bigfastapi/blog.py
bigfastapi/comments.py
bigfastapi/contact.py
bigfastapi/countries.py
bigfastapi/credit.py
bigfastapi/custom_oauth.py
bigfastapi/email.py
bigfastapi/faq.py
bigfastapi/files.py
bigfastapi/google_auth.py
bigfastapi/import_progress.py
bigfastapi/landing_page.py
bigfastapi/menu.py
bigfastapi/notification.py
bigfastapi/organization.py
bigfastapi/pdfs.py
bigfastapi/plans.py
bigfastapi/product_prices.py
bigfastapi/products.py
bigfastapi/qrcode.py
bigfastapi/receipts.py
bigfastapi/settings.py
bigfastapi/sms.py
bigfastapi/stock.py
bigfastapi/subscription.py
bigfastapi/tutorial.py
bigfastapi/users.py
bigfastapi/wallet.py
bigfastapi/core/__init__.py
bigfastapi/core/helpers.py
bigfastapi/core/messages.py
bigfastapi/core/validator.py
bigfastapi/data/bank.json
bigfastapi/data/countries.json
bigfastapi/data/dialcode.json
bigfastapi/data/menu.json
bigfastapi/data/qrcode.json
bigfastapi/db/__init__.py
bigfastapi/db/database.py
bigfastapi/models/__init__.py
bigfastapi/models/activity_log_models.py
bigfastapi/models/auth_models.py
bigfastapi/models/bank_models.py
bigfastapi/models/blog_models.py
bigfastapi/models/comments_models.py
bigfastapi/models/contact_info_models.py
bigfastapi/models/contact_model.py
bigfastapi/models/credit_wallet_models.py
bigfastapi/models/email_models.py
bigfastapi/models/extra_info_models.py
bigfastapi/models/faq_models.py
bigfastapi/models/file_import_models.py
bigfastapi/models/file_models.py
bigfastapi/models/landing_page_models.py
bigfastapi/models/location_models.py
bigfastapi/models/menu_models.py
bigfastapi/models/notification_models.py
bigfastapi/models/organization_models.py
bigfastapi/models/plan_models.py
bigfastapi/models/receipt_models.py
bigfastapi/models/settings_models.py
bigfastapi/models/sms_models.py
bigfastapi/models/subscription_models.py
bigfastapi/models/tutorial_models.py
bigfastapi-0.6.1.dist-info/LICENSE
bigfastapi-0.6.1.dist-info/METADATA
bigfastapi-0.6.1.dist-info/WHEEL
bigfastapi-0.6.1.dist-info/top_level.txt
bigfastapi-0.6.1.dist-info/RECORD
