Metadata-Version: 2.1
Name: bigfastapi
Version: 0.6.1
Summary: Adding lots of functionality to FastAPI
Home-page: https://bigfa.st/
Author: BigFastAPI Team
Author-email: support@bigfa.st
License: UNKNOWN
Project-URL: Bug Reports, https://github.com/bigfastcode/bigfastapi/issues
Project-URL: Funding, https://bigfa.st/
Project-URL: Source, https://github.com/bigfastcode/bigfastapi
Keywords: fastapi,bigfastapi,auth
Platform: UNKNOWN
Classifier: Programming Language :: Python :: 3
Classifier: License :: OSI Approved :: MIT License
Classifier: Operating System :: OS Independent
Classifier: Development Status :: 3 - Alpha
Classifier: Intended Audience :: Developers
Classifier: Topic :: Software Development :: Build Tools
Requires-Python: >=3.8
License-File: LICENSE
Requires-Dist: Jinja2
Requires-Dist: fastapi
Requires-Dist: wheel
Requires-Dist: uvicorn
Requires-Dist: aioredis
Requires-Dist: aiosmtplib
Requires-Dist: anyio
Requires-Dist: alembic
Requires-Dist: asgiref
Requires-Dist: async-timeout
Requires-Dist: blinker
Requires-Dist: certifi
Requires-Dist: cffi
Requires-Dist: charset-normalizer
Requires-Dist: click
Requires-Dist: dnspython
Requires-Dist: email-validator
Requires-Dist: fastapi-mail
Requires-Dist: fastapi-utils
Requires-Dist: greenlet
Requires-Dist: h11
Requires-Dist: idna
Requires-Dist: MarkupSafe
Requires-Dist: packaging
Requires-Dist: passlib
Requires-Dist: python-jose
Requires-Dist: pdfkit
Requires-Dist: pycparser
Requires-Dist: pydantic
Requires-Dist: fastapi-pagination
Requires-Dist: PyJWT
Requires-Dist: pyparsing
Requires-Dist: authlib
Requires-Dist: qrcode
Requires-Dist: python-decouple
Requires-Dist: python-dotenv
Requires-Dist: cryptography
Requires-Dist: python-jose[cryptography]
Requires-Dist: python-multipart
Requires-Dist: PyYAML
Requires-Dist: requests
Requires-Dist: rfc3986
Requires-Dist: six
Requires-Dist: sniffio
Requires-Dist: sortedcontainers
Requires-Dist: SQLAlchemy
Requires-Dist: starlette
Requires-Dist: typing-extensions
Requires-Dist: watchgod
Requires-Dist: websockets
Requires-Dist: validators
Requires-Dist: pytest
Requires-Dist: itsdangerous
